[
    {
        "urlPath": "/assets/blt219731602ae0e670",
        "uid": "blt219731602ae0e670",
        "content_type": "image/png",
        "file_size": "541022",
        "tags": [],
        "filename": "Golden_Bear_Steerhide_Moto_(3).png",
        "url": "https://images.contentstack.io/v3/assets/bltc91ab68f0b5e7b84/blt219731602ae0e670/612f160606f9881e7afed820/Golden_Bear_Steerhide_Moto_(3).png",
        "ACL": {},
        "is_dir": false,
        "_version": 1,
        "title": "Golden_Bear_Steerhide_Moto_(3).png",
        "publish_details": []
    }
]