{"title":"Category","uid":"category","schema":[{"display_name":"Title","uid":"title","data_type":"text","mandatory":true,"unique":true,"field_metadata":{"_default":true,"version":3},"multiple":false,"non_localizable":false},{"display_name":"URL","uid":"url","data_type":"text","mandatory":false,"field_metadata":{"_default":true,"version":3},"multiple":false,"unique":false,"non_localizable":false},{"data_type":"text","display_name":"Description","uid":"description","field_metadata":{"multiline":true,"version":3},"multiple":false,"mandatory":false,"unique":false,"non_localizable":false}],"description":"It contains category section content.","options":{"is_page":true,"singleton":false,"title":"title","url_pattern":"/:title","url_prefix":"/category/"}}