{
    "bltf7b86b8aeb28da50": {
        "title": "MVMT Rallye Green Sandstone 2",
        "url": "/product/bltf7826820436381ff",
        "description": "Hand-painted moon, Moon retrograde with precision of 122 years, Moon returns backwards to zero at the end of its cycle every 29 days 12 hours and 44 minutes, Scratch resistant anti-reflective domed sapphire crystal, Crown decorated with a sapphire stone Swiss manual wind high precision mechanical movement with Haute Horlogerie finishing, Calibre G1769, 21'600 A/h (3Hz), Incabloc shock absorber, 29 jewels, Power reserve of 96 hours. Water resistant to 3 ATM/30 meters/99 feet, Hand-sewn blue alligator leather strap , 18k white gold push button deployment buckle, Fits up to a 10 inch wrist",
        "featured_image": [
            {
                "uid": "blt57acaeefc337bd68",
                "created_at": "2021-09-01T05:57:41.280Z",
                "updated_at": "2021-09-01T05:57:41.280Z",
                "content_type": "image/png",
                "file_size": "35141",
                "tags": [],
                "filename": "Unimatic_U1-E_Diver.png",
                "url": "https://images.contentstack.io/v3/assets/bltc91ab68f0b5e7b84/blt57acaeefc337bd68/612f1655d9ff54131218ae6a/Unimatic_U1-E_Diver.png",
                "ACL": [],
                "is_dir": false,
                "_version": 1,
                "title": "Unimatic_U1-E_Diver.png",
                "publish_details": [
                    {
                        "environment": "blt0677a9c52fcd5de1",
                        "locale": "en-us",
                        "time": "2021-09-01T05:57:43.144Z",
                        "user": "bltc359c2d884f0888e",
                        "version": 1
                    },
                    {
                        "environment": "bltf9d34c6dfb34d221",
                        "locale": "en-us",
                        "time": "2021-09-01T05:57:43.144Z",
                        "user": "bltc359c2d884f0888e",
                        "version": 1
                    },
                    {
                        "environment": "blt3e578964e5ba0afe",
                        "locale": "en-us",
                        "time": "2021-09-01T05:57:43.144Z",
                        "user": "bltc359c2d884f0888e",
                        "version": 1
                    }
                ]
            },
            {
                "uid": "blt2f705cacdc5957db",
                "created_at": "2021-09-01T05:56:42.269Z",
                "updated_at": "2021-09-01T05:56:42.269Z",
                "content_type": "image/png",
                "file_size": "19786",
                "tags": [],
                "filename": "MVMT_Rallye_Green_Sandstone_3.png",
                "url": "https://images.contentstack.io/v3/assets/bltc91ab68f0b5e7b84/blt2f705cacdc5957db/612f161a932fbb12e7dc7519/MVMT_Rallye_Green_Sandstone_3.png",
                "ACL": [],
                "is_dir": false,
                "parent_uid": null,
                "_version": 1,
                "title": "MVMT_Rallye_Green_Sandstone_3.png",
                "publish_details": [
                    {
                        "environment": "blt0677a9c52fcd5de1",
                        "locale": "en-us",
                        "time": "2021-09-01T05:56:43.975Z",
                        "user": "bltc359c2d884f0888e",
                        "version": 1
                    },
                    {
                        "environment": "blt3e578964e5ba0afe",
                        "locale": "en-us",
                        "time": "2021-09-01T05:56:43.975Z",
                        "user": "bltc359c2d884f0888e",
                        "version": 1
                    },
                    {
                        "environment": "bltf9d34c6dfb34d221",
                        "locale": "en-us",
                        "time": "2021-09-01T05:56:43.975Z",
                        "user": "bltc359c2d884f0888e",
                        "version": 1
                    }
                ]
            },
            {
                "uid": "blteccabffada65846c",
                "created_at": "2021-09-01T05:56:38.878Z",
                "updated_at": "2021-09-01T05:56:38.878Z",
                "content_type": "image/png",
                "file_size": "22168",
                "tags": [],
                "filename": "MVMT_Rallye_Green_Sandstone_2.png",
                "url": "https://images.contentstack.io/v3/assets/bltc91ab68f0b5e7b84/blteccabffada65846c/612f1616981a381cf3358c3a/MVMT_Rallye_Green_Sandstone_2.png",
                "ACL": [],
                "is_dir": false,
                "_version": 1,
                "title": "MVMT_Rallye_Green_Sandstone_2.png",
                "publish_details": [
                    {
                        "environment": "bltf9d34c6dfb34d221",
                        "locale": "en-us",
                        "time": "2021-09-01T05:56:40.698Z",
                        "user": "bltc359c2d884f0888e",
                        "version": 1
                    },
                    {
                        "environment": "blt3e578964e5ba0afe",
                        "locale": "en-us",
                        "time": "2021-09-01T05:56:40.698Z",
                        "user": "bltc359c2d884f0888e",
                        "version": 1
                    },
                    {
                        "environment": "blt0677a9c52fcd5de1",
                        "locale": "en-us",
                        "time": "2021-09-01T05:56:40.698Z",
                        "user": "bltc359c2d884f0888e",
                        "version": 1
                    }
                ]
            }
        ],
        "categories": [
            {
                "uid": "blt526e34cfde0ddb9b",
                "_content_type_uid": "category"
            }
        ],
        "related_products": [
            {
                "uid": "blt2eec3bb34477df60",
                "_content_type_uid": "product"
            },
            {
                "uid": "bltceccaa78087a130e",
                "_content_type_uid": "product"
            },
            {
                "uid": "blt7ec0e389746cae2e",
                "_content_type_uid": "product"
            }
        ],
        "tweet_text": "",
        "seo": {
            "description": "",
            "keyword": "",
            "block_indexing": false
        },
        "tags": [],
        "locale": "en-us",
        "ACL": {},
        "_in_progress": false,
        "number": 150,
        "extension_product_link": [],
        "uid": "bltf7b86b8aeb28da50",
        "_version": 6,
        "publish_details": [
            {
                "environment": "blt3e578964e5ba0afe",
                "locale": "en-us",
                "time": "2021-09-09T07:03:13.305Z",
                "user": "bltd5d70bb484fce3ae",
                "version": 6
            },
            {
                "environment": "blt0677a9c52fcd5de1",
                "locale": "en-us",
                "time": "2021-09-09T07:03:13.297Z",
                "user": "bltd5d70bb484fce3ae",
                "version": 6
            },
            {
                "environment": "bltf9d34c6dfb34d221",
                "locale": "en-us",
                "time": "2021-09-09T07:03:13.343Z",
                "user": "bltd5d70bb484fce3ae",
                "version": 6
            }
        ]
    },
    "blt38c5b2de6c748ba5": {
        "title": "Ocean 600M Automatic Chronometer Brown",
        "url": "/product/blt4ad5f2d7a4780dd4",
        "description": "Silver-tone stainless steel case with a silver-tone stainless steel bracelet. Uni-directional rotating black ceramic bezel. Black dial with luminous silver-tone hands and index hour markers. Arabic numerals mark the 6, 9 and 12 o'clock positions. minute markers around the outer rim. Dial Type: Analog. Luminescent hands and markers. Date display at the 3 o'clock position. Omega Calibre 8520 automatic movement with a 50-hour power reserve. Scratch resistant sapphire crystal. Screw down crown. Transparent case back. Round case shape, case size: 37.5 mm, case thickness: 10 mm. Band width: 18 mm, band length: 8.5 inches. Fold over clasp. Water resistant at 600 meters / 2000 feet. Functions: date, hour, minute, second, chronometer. Additional Info: features a helium escapement valve located on the edge of the case at the 10 o'clock position. Luxury watch style. Watch label: Swiss Made. Omega Planet Ocean 600M Automatic Chronometer Black Dial Mid-Size Watch 232.30.38.20.01.001.",
        "featured_image": [
            {
                "uid": "blta1233348d516cd43",
                "created_at": "2021-09-01T05:58:17.188Z",
                "updated_at": "2021-09-01T05:58:17.188Z",
                "content_type": "image/png",
                "file_size": "28686",
                "tags": [],
                "filename": "MVMT_Cloud_Silver.png",
                "url": "https://images.contentstack.io/v3/assets/bltc91ab68f0b5e7b84/blta1233348d516cd43/612f167956ed301db65204ec/MVMT_Cloud_Silver.png",
                "ACL": [],
                "is_dir": false,
                "_version": 1,
                "title": "MVMT_Cloud_Silver.png",
                "publish_details": [
                    {
                        "environment": "bltf9d34c6dfb34d221",
                        "locale": "en-us",
                        "time": "2021-09-01T05:58:18.974Z",
                        "user": "bltc359c2d884f0888e",
                        "version": 1
                    },
                    {
                        "environment": "blt3e578964e5ba0afe",
                        "locale": "en-us",
                        "time": "2021-09-01T05:58:18.974Z",
                        "user": "bltc359c2d884f0888e",
                        "version": 1
                    },
                    {
                        "environment": "blt0677a9c52fcd5de1",
                        "locale": "en-us",
                        "time": "2021-09-01T05:58:18.974Z",
                        "user": "bltc359c2d884f0888e",
                        "version": 1
                    }
                ]
            },
            {
                "uid": "blte1e73ea322e92201",
                "created_at": "2021-09-01T05:55:58.230Z",
                "updated_at": "2021-09-01T05:55:58.230Z",
                "content_type": "image/png",
                "file_size": "203235",
                "tags": [],
                "filename": "MVMT_Cloud_Silver_(3).png",
                "url": "https://images.contentstack.io/v3/assets/bltc91ab68f0b5e7b84/blte1e73ea322e92201/612f15ee0f5631145847b03c/MVMT_Cloud_Silver_(3).png",
                "ACL": [],
                "is_dir": false,
                "_version": 1,
                "title": "MVMT_Cloud_Silver_(3).png",
                "publish_details": [
                    {
                        "environment": "blt0677a9c52fcd5de1",
                        "locale": "en-us",
                        "time": "2021-09-01T05:55:59.926Z",
                        "user": "bltc359c2d884f0888e",
                        "version": 1
                    },
                    {
                        "environment": "bltf9d34c6dfb34d221",
                        "locale": "en-us",
                        "time": "2021-09-01T05:55:59.926Z",
                        "user": "bltc359c2d884f0888e",
                        "version": 1
                    },
                    {
                        "environment": "blt3e578964e5ba0afe",
                        "locale": "en-us",
                        "time": "2021-09-01T05:55:59.926Z",
                        "user": "bltc359c2d884f0888e",
                        "version": 1
                    }
                ]
            },
            {
                "uid": "bltb63c5cbc947844d4",
                "created_at": "2021-09-01T05:54:59.447Z",
                "updated_at": "2021-09-01T05:54:59.447Z",
                "content_type": "image/png",
                "file_size": "94313",
                "tags": [],
                "filename": "MVMT_Cloud_Silver_(2).png",
                "url": "https://images.contentstack.io/v3/assets/bltc91ab68f0b5e7b84/bltb63c5cbc947844d4/612f15b3a0513b0d7a38ad1c/MVMT_Cloud_Silver_(2).png",
                "ACL": [],
                "is_dir": false,
                "_version": 1,
                "title": "MVMT_Cloud_Silver_(2).png",
                "publish_details": [
                    {
                        "environment": "blt0677a9c52fcd5de1",
                        "locale": "en-us",
                        "time": "2021-09-01T05:55:01.380Z",
                        "user": "bltc359c2d884f0888e",
                        "version": 1
                    },
                    {
                        "environment": "bltf9d34c6dfb34d221",
                        "locale": "en-us",
                        "time": "2021-09-01T05:55:01.380Z",
                        "user": "bltc359c2d884f0888e",
                        "version": 1
                    },
                    {
                        "environment": "blt3e578964e5ba0afe",
                        "locale": "en-us",
                        "time": "2021-09-01T07:56:24.577Z",
                        "user": "bltd5d70bb484fce3ae",
                        "version": 1
                    }
                ]
            }
        ],
        "categories": [
            {
                "uid": "blt5cb2771ed6bcf69c",
                "_content_type_uid": "category"
            }
        ],
        "related_products": [
            {
                "uid": "bltf7b86b8aeb28da50",
                "_content_type_uid": "product"
            },
            {
                "uid": "blt98b7b713fc82c887",
                "_content_type_uid": "product"
            },
            {
                "uid": "blt912a4b73ec3ace96",
                "_content_type_uid": "product"
            },
            {
                "uid": "blt2eec3bb34477df60",
                "_content_type_uid": "product"
            },
            {
                "uid": "blt7ec0e389746cae2e",
                "_content_type_uid": "product"
            },
            {
                "uid": "blt06593f89b4b0207d",
                "_content_type_uid": "product"
            },
            {
                "uid": "blt46db151f0b8fb105",
                "_content_type_uid": "product"
            },
            {
                "uid": "blt7f6a22a1a5ba14e9",
                "_content_type_uid": "product"
            }
        ],
        "tweet_text": "",
        "seo": {
            "description": "",
            "keyword": "",
            "block_indexing": false
        },
        "tags": [],
        "locale": "en-us",
        "ACL": {},
        "_in_progress": false,
        "number": 150,
        "extension_product_link": [],
        "uid": "blt38c5b2de6c748ba5",
        "_version": 6,
        "publish_details": [
            {
                "environment": "blt3e578964e5ba0afe",
                "locale": "en-us",
                "time": "2021-09-09T07:03:13.913Z",
                "user": "bltd5d70bb484fce3ae",
                "version": 6
            },
            {
                "environment": "bltf9d34c6dfb34d221",
                "locale": "en-us",
                "time": "2021-09-09T07:03:13.913Z",
                "user": "bltd5d70bb484fce3ae",
                "version": 6
            },
            {
                "environment": "blt0677a9c52fcd5de1",
                "locale": "en-us",
                "time": "2021-09-09T07:03:13.913Z",
                "user": "bltd5d70bb484fce3ae",
                "version": 6
            }
        ]
    },
    "blt98b7b713fc82c887": {
        "title": "New Wayfarer Sunglasses 2",
        "url": "/product/blt96f6287cde2004c1",
        "description": "The classic Wayfarer is a comfortable, fashionable, and durable pair of sunglasses for women and men. The combination of black durable plastic frame with green glass lenses is iconic.100% UV PROTECTION: To protect your eyes from harmful UV rays, these Wayfarer sunglasses include glass lenses that are coated with 100% UV protection. The 52 mm x 37.6 mm lenses are durable and polarized. Eliminates glare REDUCE EYE STRAIN: Unisex Wayfarer sunglasses feature precision-cut lenses that help reduce eye strain while outdoors. They are great to wear on both hazy and bright days.</p><p>DURABLE ACETATE FRAMES: Our polarized Wayfarer sunglasses are incredibly durable. The frame is made from lightweight yet strong acetate construction. The bridge measures 18 mm, and the arms are 145 mm for an easy, comfortable fit.</p><p>MULTIPLE FRAME AND LENS COLORS: These sunglasses for women and men are designed in multiple frame and lens colors. Find a color combination that fits your personal brand and style.</p>",
        "featured_image": [
            {
                "uid": "blt3455714cbdf73559",
                "created_at": "2021-09-01T05:58:41.922Z",
                "updated_at": "2021-09-01T05:58:41.922Z",
                "content_type": "image/png",
                "file_size": "8244",
                "tags": [],
                "filename": "New_Wayfarer_Sunglasses_(3).png",
                "url": "https://images.contentstack.io/v3/assets/bltc91ab68f0b5e7b84/blt3455714cbdf73559/612f16913dc61a23f66e1917/New_Wayfarer_Sunglasses_(3).png",
                "ACL": [],
                "is_dir": false,
                "_version": 1,
                "title": "New_Wayfarer_Sunglasses_(3).png",
                "publish_details": [
                    {
                        "environment": "blt3e578964e5ba0afe",
                        "locale": "en-us",
                        "time": "2021-09-01T05:58:44.755Z",
                        "user": "bltc359c2d884f0888e",
                        "version": 1
                    },
                    {
                        "environment": "blt0677a9c52fcd5de1",
                        "locale": "en-us",
                        "time": "2021-09-01T05:58:44.755Z",
                        "user": "bltc359c2d884f0888e",
                        "version": 1
                    },
                    {
                        "environment": "bltf9d34c6dfb34d221",
                        "locale": "en-us",
                        "time": "2021-09-01T05:58:44.755Z",
                        "user": "bltc359c2d884f0888e",
                        "version": 1
                    }
                ]
            },
            {
                "uid": "blt34cecea277fce356",
                "created_at": "2021-09-01T05:56:03.457Z",
                "updated_at": "2021-09-01T05:56:03.457Z",
                "content_type": "image/png",
                "file_size": "28346",
                "tags": [],
                "filename": "New_Wayfarer_Sunglasses_(2).png",
                "url": "https://images.contentstack.io/v3/assets/bltc91ab68f0b5e7b84/blt34cecea277fce356/612f15f316597c1021ce4243/New_Wayfarer_Sunglasses_(2).png",
                "ACL": [],
                "is_dir": false,
                "parent_uid": null,
                "_version": 1,
                "title": "New_Wayfarer_Sunglasses_(2).png",
                "publish_details": [
                    {
                        "environment": "bltf9d34c6dfb34d221",
                        "locale": "en-us",
                        "time": "2021-09-01T05:56:05.277Z",
                        "user": "bltc359c2d884f0888e",
                        "version": 1
                    },
                    {
                        "environment": "blt3e578964e5ba0afe",
                        "locale": "en-us",
                        "time": "2021-09-01T05:56:05.277Z",
                        "user": "bltc359c2d884f0888e",
                        "version": 1
                    },
                    {
                        "environment": "blt0677a9c52fcd5de1",
                        "locale": "en-us",
                        "time": "2021-09-01T05:56:05.277Z",
                        "user": "bltc359c2d884f0888e",
                        "version": 1
                    }
                ]
            },
            {
                "uid": "bltb66ac0c17e3201f4",
                "created_at": "2021-09-01T05:57:19.651Z",
                "updated_at": "2021-09-01T05:57:19.651Z",
                "content_type": "image/png",
                "file_size": "38875",
                "tags": [],
                "filename": "New_Wayfarer_Sunglasses_(1).png",
                "url": "https://images.contentstack.io/v3/assets/bltc91ab68f0b5e7b84/bltb66ac0c17e3201f4/612f163f428b53254db3afc2/New_Wayfarer_Sunglasses_(1).png",
                "ACL": [],
                "is_dir": false,
                "_version": 1,
                "title": "New_Wayfarer_Sunglasses_(1).png",
                "publish_details": [
                    {
                        "environment": "bltf9d34c6dfb34d221",
                        "locale": "en-us",
                        "time": "2021-09-01T05:57:21.352Z",
                        "user": "bltc359c2d884f0888e",
                        "version": 1
                    },
                    {
                        "environment": "blt3e578964e5ba0afe",
                        "locale": "en-us",
                        "time": "2021-09-01T05:57:21.352Z",
                        "user": "bltc359c2d884f0888e",
                        "version": 1
                    },
                    {
                        "environment": "blt0677a9c52fcd5de1",
                        "locale": "en-us",
                        "time": "2021-09-01T05:57:21.352Z",
                        "user": "bltc359c2d884f0888e",
                        "version": 1
                    }
                ]
            }
        ],
        "categories": [
            {
                "uid": "blt526e34cfde0ddb9b",
                "_content_type_uid": "category"
            }
        ],
        "related_products": [
            {
                "uid": "blt912a4b73ec3ace96",
                "_content_type_uid": "product"
            },
            {
                "uid": "blt2eec3bb34477df60",
                "_content_type_uid": "product"
            },
            {
                "uid": "bltceccaa78087a130e",
                "_content_type_uid": "product"
            }
        ],
        "tweet_text": "",
        "seo": {
            "description": "",
            "keyword": "",
            "block_indexing": false
        },
        "tags": [],
        "locale": "en-us",
        "ACL": {},
        "_in_progress": false,
        "number": 300,
        "extension_product_link": [],
        "uid": "blt98b7b713fc82c887",
        "_version": 6,
        "publish_details": [
            {
                "environment": "blt3e578964e5ba0afe",
                "locale": "en-us",
                "time": "2021-09-09T07:03:13.385Z",
                "user": "bltd5d70bb484fce3ae",
                "version": 6
            },
            {
                "environment": "bltf9d34c6dfb34d221",
                "locale": "en-us",
                "time": "2021-09-09T07:03:13.498Z",
                "user": "bltd5d70bb484fce3ae",
                "version": 6
            },
            {
                "environment": "blt0677a9c52fcd5de1",
                "locale": "en-us",
                "time": "2021-09-09T07:03:13.406Z",
                "user": "bltd5d70bb484fce3ae",
                "version": 6
            }
        ]
    },
    "blt912a4b73ec3ace96": {
        "title": "New Wayfarer Sunglasses",
        "url": "/product/blt7b5ccc2227098a3e",
        "description": "The classic Wayfarer is a comfortable, fashionable, and durable pair of sunglasses for women and men. The combination of black durable plastic frame with green glass lenses is iconic. 100% UV PROTECTION: To protect your eyes from harmful UV rays, these Wayfarer sunglasses include glass lenses that are coated with 100% UV protection. The 52 mm x 37.6 mm lenses are durable and polarized. Eliminates glare REDUCE EYE STRAIN: Unisex Wayfarer sunglasses feature precision-cut lenses that help reduce eye strain while outdoors. They are great to wear on both hazy and bright days. DURABLE ACETATE FRAMES: Our polarized Wayfarer sunglasses are incredibly durable. The frame is made from lightweight yet strong acetate construction. The bridge measures 18 mm, and the arms are 145 mm for an easy, comfortable fit. MULTIPLE FRAME AND LENS COLORS: These sunglasses for women and men are designed in multiple frame and lens colors. Find a color combination that fits your personal brand and style.",
        "featured_image": [
            {
                "uid": "blt3455714cbdf73559",
                "created_at": "2021-09-01T05:58:41.922Z",
                "updated_at": "2021-09-01T05:58:41.922Z",
                "content_type": "image/png",
                "file_size": "8244",
                "tags": [],
                "filename": "New_Wayfarer_Sunglasses_(3).png",
                "url": "https://images.contentstack.io/v3/assets/bltc91ab68f0b5e7b84/blt3455714cbdf73559/612f16913dc61a23f66e1917/New_Wayfarer_Sunglasses_(3).png",
                "ACL": [],
                "is_dir": false,
                "_version": 1,
                "title": "New_Wayfarer_Sunglasses_(3).png",
                "publish_details": [
                    {
                        "environment": "blt3e578964e5ba0afe",
                        "locale": "en-us",
                        "time": "2021-09-01T05:58:44.755Z",
                        "user": "bltc359c2d884f0888e",
                        "version": 1
                    },
                    {
                        "environment": "blt0677a9c52fcd5de1",
                        "locale": "en-us",
                        "time": "2021-09-01T05:58:44.755Z",
                        "user": "bltc359c2d884f0888e",
                        "version": 1
                    },
                    {
                        "environment": "bltf9d34c6dfb34d221",
                        "locale": "en-us",
                        "time": "2021-09-01T05:58:44.755Z",
                        "user": "bltc359c2d884f0888e",
                        "version": 1
                    }
                ]
            },
            {
                "uid": "blt34cecea277fce356",
                "created_at": "2021-09-01T05:56:03.457Z",
                "updated_at": "2021-09-01T05:56:03.457Z",
                "content_type": "image/png",
                "file_size": "28346",
                "tags": [],
                "filename": "New_Wayfarer_Sunglasses_(2).png",
                "url": "https://images.contentstack.io/v3/assets/bltc91ab68f0b5e7b84/blt34cecea277fce356/612f15f316597c1021ce4243/New_Wayfarer_Sunglasses_(2).png",
                "ACL": [],
                "is_dir": false,
                "parent_uid": null,
                "_version": 1,
                "title": "New_Wayfarer_Sunglasses_(2).png",
                "publish_details": [
                    {
                        "environment": "bltf9d34c6dfb34d221",
                        "locale": "en-us",
                        "time": "2021-09-01T05:56:05.277Z",
                        "user": "bltc359c2d884f0888e",
                        "version": 1
                    },
                    {
                        "environment": "blt3e578964e5ba0afe",
                        "locale": "en-us",
                        "time": "2021-09-01T05:56:05.277Z",
                        "user": "bltc359c2d884f0888e",
                        "version": 1
                    },
                    {
                        "environment": "blt0677a9c52fcd5de1",
                        "locale": "en-us",
                        "time": "2021-09-01T05:56:05.277Z",
                        "user": "bltc359c2d884f0888e",
                        "version": 1
                    }
                ]
            },
            {
                "uid": "bltb66ac0c17e3201f4",
                "created_at": "2021-09-01T05:57:19.651Z",
                "updated_at": "2021-09-01T05:57:19.651Z",
                "content_type": "image/png",
                "file_size": "38875",
                "tags": [],
                "filename": "New_Wayfarer_Sunglasses_(1).png",
                "url": "https://images.contentstack.io/v3/assets/bltc91ab68f0b5e7b84/bltb66ac0c17e3201f4/612f163f428b53254db3afc2/New_Wayfarer_Sunglasses_(1).png",
                "ACL": [],
                "is_dir": false,
                "_version": 1,
                "title": "New_Wayfarer_Sunglasses_(1).png",
                "publish_details": [
                    {
                        "environment": "bltf9d34c6dfb34d221",
                        "locale": "en-us",
                        "time": "2021-09-01T05:57:21.352Z",
                        "user": "bltc359c2d884f0888e",
                        "version": 1
                    },
                    {
                        "environment": "blt3e578964e5ba0afe",
                        "locale": "en-us",
                        "time": "2021-09-01T05:57:21.352Z",
                        "user": "bltc359c2d884f0888e",
                        "version": 1
                    },
                    {
                        "environment": "blt0677a9c52fcd5de1",
                        "locale": "en-us",
                        "time": "2021-09-01T05:57:21.352Z",
                        "user": "bltc359c2d884f0888e",
                        "version": 1
                    }
                ]
            }
        ],
        "categories": [
            {
                "uid": "blt526e34cfde0ddb9b",
                "_content_type_uid": "category"
            }
        ],
        "related_products": [],
        "tweet_text": "",
        "seo": {
            "description": "",
            "keyword": "",
            "block_indexing": false
        },
        "tags": [],
        "locale": "en-us",
        "ACL": {},
        "_in_progress": false,
        "number": 254,
        "extension_product_link": [],
        "uid": "blt912a4b73ec3ace96",
        "_version": 6,
        "publish_details": [
            {
                "environment": "blt3e578964e5ba0afe",
                "locale": "en-us",
                "time": "2021-09-09T07:03:13.578Z",
                "user": "bltd5d70bb484fce3ae",
                "version": 6
            },
            {
                "environment": "blt0677a9c52fcd5de1",
                "locale": "en-us",
                "time": "2021-09-09T07:03:13.575Z",
                "user": "bltd5d70bb484fce3ae",
                "version": 6
            },
            {
                "environment": "bltf9d34c6dfb34d221",
                "locale": "en-us",
                "time": "2021-09-09T07:03:13.586Z",
                "user": "bltd5d70bb484fce3ae",
                "version": 6
            }
        ]
    },
    "blt06593f89b4b0207d": {
        "title": "Oppenheimer's Lux Jacket - Bluev",
        "url": "/product/bltf3f8e3a53d7b9524",
        "description": "Size Info Narrow through the bust and shoulders.If purchasing for the first time, order one size up.XS=2-4, S=4-6, M=8-10, L=10-12, XL=14.Details &amp; Care Iconic checks line the collar and cuffs of this lightweight quilted jacket that embraces heritage styling while providing the perfect amount of warmth for transitional seasons. 25 1/2\" length (size Medium) Front button closure Point collar with hook-and-eye closure Long sleeves with button cuffs Front slip pockets Epaulets Lined 100% polyester</p> Dry clean Imported Collectors.",
        "featured_image": [
            {
                "uid": "blt26272fce2f8889a8",
                "created_at": "2021-09-01T05:57:49.548Z",
                "updated_at": "2021-09-01T05:57:49.548Z",
                "content_type": "image/png",
                "file_size": "50993",
                "tags": [],
                "filename": "Taylor_Stitch_Mendocino_Peacoat.png",
                "url": "https://images.contentstack.io/v3/assets/bltc91ab68f0b5e7b84/blt26272fce2f8889a8/612f165dee65201173ae1460/Taylor_Stitch_Mendocino_Peacoat.png",
                "ACL": [],
                "is_dir": false,
                "_version": 1,
                "title": "Taylor_Stitch_Mendocino_Peacoat.png",
                "publish_details": [
                    {
                        "environment": "bltf9d34c6dfb34d221",
                        "locale": "en-us",
                        "time": "2021-09-01T05:57:52.190Z",
                        "user": "bltc359c2d884f0888e",
                        "version": 1
                    },
                    {
                        "environment": "blt3e578964e5ba0afe",
                        "locale": "en-us",
                        "time": "2021-09-01T05:57:52.190Z",
                        "user": "bltc359c2d884f0888e",
                        "version": 1
                    },
                    {
                        "environment": "blt0677a9c52fcd5de1",
                        "locale": "en-us",
                        "time": "2021-09-01T05:57:52.190Z",
                        "user": "bltc359c2d884f0888e",
                        "version": 1
                    }
                ]
            },
            {
                "uid": "blte253300b18a356cd",
                "created_at": "2021-09-01T05:56:35.010Z",
                "updated_at": "2021-09-01T05:56:35.010Z",
                "content_type": "image/png",
                "file_size": "443264",
                "tags": [],
                "filename": "Taylor_Stitch_Mendocino_Peacoat_(3).png",
                "url": "https://images.contentstack.io/v3/assets/bltc91ab68f0b5e7b84/blte253300b18a356cd/612f16138ad1c01915c90b1a/Taylor_Stitch_Mendocino_Peacoat_(3).png",
                "ACL": [],
                "is_dir": false,
                "_version": 1,
                "title": "Taylor_Stitch_Mendocino_Peacoat_(3).png",
                "publish_details": [
                    {
                        "environment": "bltf9d34c6dfb34d221",
                        "locale": "en-us",
                        "time": "2021-09-01T05:56:36.844Z",
                        "user": "bltc359c2d884f0888e",
                        "version": 1
                    },
                    {
                        "environment": "blt0677a9c52fcd5de1",
                        "locale": "en-us",
                        "time": "2021-09-01T05:56:36.844Z",
                        "user": "bltc359c2d884f0888e",
                        "version": 1
                    },
                    {
                        "environment": "blt3e578964e5ba0afe",
                        "locale": "en-us",
                        "time": "2021-09-01T05:56:36.844Z",
                        "user": "bltc359c2d884f0888e",
                        "version": 1
                    }
                ]
            },
            {
                "uid": "blt49452b50fcc90380",
                "created_at": "2021-09-01T05:55:13.691Z",
                "updated_at": "2021-09-01T05:55:13.691Z",
                "content_type": "image/png",
                "file_size": "185734",
                "tags": [],
                "filename": "Taylor_Stitch_Mendocino_Peacoat_(2).png",
                "url": "https://images.contentstack.io/v3/assets/bltc91ab68f0b5e7b84/blt49452b50fcc90380/612f15c156ed301db65204d2/Taylor_Stitch_Mendocino_Peacoat_(2).png",
                "ACL": [],
                "is_dir": false,
                "_version": 1,
                "title": "Taylor_Stitch_Mendocino_Peacoat_(2).png",
                "publish_details": [
                    {
                        "environment": "blt0677a9c52fcd5de1",
                        "locale": "en-us",
                        "time": "2021-09-01T05:55:15.695Z",
                        "user": "bltc359c2d884f0888e",
                        "version": 1
                    },
                    {
                        "environment": "bltf9d34c6dfb34d221",
                        "locale": "en-us",
                        "time": "2021-09-01T05:55:15.695Z",
                        "user": "bltc359c2d884f0888e",
                        "version": 1
                    },
                    {
                        "environment": "blt3e578964e5ba0afe",
                        "locale": "en-us",
                        "time": "2021-09-01T05:55:15.695Z",
                        "user": "bltc359c2d884f0888e",
                        "version": 1
                    }
                ]
            }
        ],
        "categories": [
            {
                "uid": "blt073302c68bb3b3f7",
                "_content_type_uid": "category"
            }
        ],
        "related_products": [],
        "tweet_text": "",
        "seo": {
            "description": "",
            "keyword": "",
            "block_indexing": false
        },
        "tags": [],
        "locale": "en-us",
        "ACL": {},
        "_in_progress": false,
        "number": 270,
        "extension_product_link": [],
        "uid": "blt06593f89b4b0207d",
        "_version": 9,
        "publish_details": [
            {
                "environment": "blt3e578964e5ba0afe",
                "locale": "en-us",
                "time": "2021-09-09T07:03:13.592Z",
                "user": "bltd5d70bb484fce3ae",
                "version": 9
            },
            {
                "environment": "blt0677a9c52fcd5de1",
                "locale": "en-us",
                "time": "2021-09-09T07:03:13.668Z",
                "user": "bltd5d70bb484fce3ae",
                "version": 9
            },
            {
                "environment": "bltf9d34c6dfb34d221",
                "locale": "en-us",
                "time": "2021-09-09T07:03:13.670Z",
                "user": "bltd5d70bb484fce3ae",
                "version": 9
            }
        ]
    },
    "blt7ec0e389746cae2e": {
        "title": "Ocean 600M Automatic Chronometer Brown Dial Mid-Size Watch",
        "url": "/product/bltdf124f995747c4ec",
        "description": "Silver-tone stainless steel case with a silver-tone stainless steel bracelet. Uni-directional rotating black ceramic bezel. Black dial with luminous silver-tone hands and index hour markers. Arabic numerals mark the 6, 9 and 12 o'clock positions. minute markers around the outer rim. Dial Type: Analog. Luminescent hands and markers. Date display at the 3 o'clock position. Omega Calibre 8520 automatic movement with a 50-hour power reserve. Scratch resistant sapphire crystal. Screw down crown. Transparent case back. Round case shape, case size: 37.5 mm, case thickness: 10 mm. Band width: 18 mm, band length: 8.5 inches. Fold over clasp. Water resistant at 600 meters / 2000 feet. Functions: date, hour, minute, second, chronometer. Additional Info: features a helium escapement valve located on the edge of the case at the 10 o'clock position. Luxury watch style. Watch label: Swiss Made. Omega Planet Ocean 600M Automatic Chronometer Black Dial Mid-Size Watch 232.30.38.20.01.001.",
        "featured_image": [
            {
                "uid": "blta1233348d516cd43",
                "created_at": "2021-09-01T05:58:17.188Z",
                "updated_at": "2021-09-01T05:58:17.188Z",
                "content_type": "image/png",
                "file_size": "28686",
                "tags": [],
                "filename": "MVMT_Cloud_Silver.png",
                "url": "https://images.contentstack.io/v3/assets/bltc91ab68f0b5e7b84/blta1233348d516cd43/612f167956ed301db65204ec/MVMT_Cloud_Silver.png",
                "ACL": [],
                "is_dir": false,
                "_version": 1,
                "title": "MVMT_Cloud_Silver.png",
                "publish_details": [
                    {
                        "environment": "bltf9d34c6dfb34d221",
                        "locale": "en-us",
                        "time": "2021-09-01T05:58:18.974Z",
                        "user": "bltc359c2d884f0888e",
                        "version": 1
                    },
                    {
                        "environment": "blt3e578964e5ba0afe",
                        "locale": "en-us",
                        "time": "2021-09-01T05:58:18.974Z",
                        "user": "bltc359c2d884f0888e",
                        "version": 1
                    },
                    {
                        "environment": "blt0677a9c52fcd5de1",
                        "locale": "en-us",
                        "time": "2021-09-01T05:58:18.974Z",
                        "user": "bltc359c2d884f0888e",
                        "version": 1
                    }
                ]
            },
            {
                "uid": "blte1e73ea322e92201",
                "created_at": "2021-09-01T05:55:58.230Z",
                "updated_at": "2021-09-01T05:55:58.230Z",
                "content_type": "image/png",
                "file_size": "203235",
                "tags": [],
                "filename": "MVMT_Cloud_Silver_(3).png",
                "url": "https://images.contentstack.io/v3/assets/bltc91ab68f0b5e7b84/blte1e73ea322e92201/612f15ee0f5631145847b03c/MVMT_Cloud_Silver_(3).png",
                "ACL": [],
                "is_dir": false,
                "_version": 1,
                "title": "MVMT_Cloud_Silver_(3).png",
                "publish_details": [
                    {
                        "environment": "blt0677a9c52fcd5de1",
                        "locale": "en-us",
                        "time": "2021-09-01T05:55:59.926Z",
                        "user": "bltc359c2d884f0888e",
                        "version": 1
                    },
                    {
                        "environment": "bltf9d34c6dfb34d221",
                        "locale": "en-us",
                        "time": "2021-09-01T05:55:59.926Z",
                        "user": "bltc359c2d884f0888e",
                        "version": 1
                    },
                    {
                        "environment": "blt3e578964e5ba0afe",
                        "locale": "en-us",
                        "time": "2021-09-01T05:55:59.926Z",
                        "user": "bltc359c2d884f0888e",
                        "version": 1
                    }
                ]
            },
            {
                "uid": "bltfc4e0fe12496733a",
                "created_at": "2021-09-01T05:55:32.515Z",
                "updated_at": "2021-09-01T05:55:32.515Z",
                "content_type": "image/png",
                "file_size": "28686",
                "tags": [],
                "filename": "MVMT_Cloud_Silver_(1).png",
                "url": "https://images.contentstack.io/v3/assets/bltc91ab68f0b5e7b84/bltfc4e0fe12496733a/612f15d43eb0930d8042ae4f/MVMT_Cloud_Silver_(1).png",
                "ACL": [],
                "is_dir": false,
                "_version": 1,
                "title": "MVMT_Cloud_Silver_(1).png",
                "publish_details": [
                    {
                        "environment": "bltf9d34c6dfb34d221",
                        "locale": "en-us",
                        "time": "2021-09-01T05:55:34.153Z",
                        "user": "bltc359c2d884f0888e",
                        "version": 1
                    },
                    {
                        "environment": "blt0677a9c52fcd5de1",
                        "locale": "en-us",
                        "time": "2021-09-01T05:55:34.153Z",
                        "user": "bltc359c2d884f0888e",
                        "version": 1
                    },
                    {
                        "environment": "blt3e578964e5ba0afe",
                        "locale": "en-us",
                        "time": "2021-09-01T05:55:34.153Z",
                        "user": "bltc359c2d884f0888e",
                        "version": 1
                    }
                ]
            }
        ],
        "categories": [
            {
                "uid": "blt5cb2771ed6bcf69c",
                "_content_type_uid": "category"
            }
        ],
        "related_products": [
            {
                "uid": "blt2eec3bb34477df60",
                "_content_type_uid": "product"
            }
        ],
        "tweet_text": "",
        "seo": {
            "description": "",
            "keyword": "",
            "block_indexing": false
        },
        "tags": [],
        "locale": "en-us",
        "ACL": {},
        "_in_progress": false,
        "number": 217,
        "extension_product_link": [],
        "uid": "blt7ec0e389746cae2e",
        "_version": 6,
        "publish_details": [
            {
                "environment": "blt3e578964e5ba0afe",
                "locale": "en-us",
                "time": "2021-09-09T07:03:13.188Z",
                "user": "bltd5d70bb484fce3ae",
                "version": 6
            },
            {
                "environment": "blt0677a9c52fcd5de1",
                "locale": "en-us",
                "time": "2021-09-09T07:03:13.313Z",
                "user": "bltd5d70bb484fce3ae",
                "version": 6
            },
            {
                "environment": "bltf9d34c6dfb34d221",
                "locale": "en-us",
                "time": "2021-09-09T07:03:13.267Z",
                "user": "bltd5d70bb484fce3ae",
                "version": 6
            }
        ]
    },
    "bltceccaa78087a130e": {
        "title": "NAUTOSCAPH III - Black Sunray Dial Mens Watch",
        "url": "/product/blt3ac3e878350cb7e9",
        "description": "Imported Stainless steel watch with unidirectional black bezel and dial with luminous hour markers and date display at three o'clock 41 mm stainless steel case with synthetic-sapphire dial window Swiss quartz movement with analog display Rubber band with buckle closure Water resistant to 200 m (660 ft): In general, suitable for professional marine activity and serious surface water sports, but not scuba diving.",
        "featured_image": [
            {
                "uid": "blt57acaeefc337bd68",
                "created_at": "2021-09-01T05:57:41.280Z",
                "updated_at": "2021-09-01T05:57:41.280Z",
                "content_type": "image/png",
                "file_size": "35141",
                "tags": [],
                "filename": "Unimatic_U1-E_Diver.png",
                "url": "https://images.contentstack.io/v3/assets/bltc91ab68f0b5e7b84/blt57acaeefc337bd68/612f1655d9ff54131218ae6a/Unimatic_U1-E_Diver.png",
                "ACL": [],
                "is_dir": false,
                "_version": 1,
                "title": "Unimatic_U1-E_Diver.png",
                "publish_details": [
                    {
                        "environment": "blt0677a9c52fcd5de1",
                        "locale": "en-us",
                        "time": "2021-09-01T05:57:43.144Z",
                        "user": "bltc359c2d884f0888e",
                        "version": 1
                    },
                    {
                        "environment": "bltf9d34c6dfb34d221",
                        "locale": "en-us",
                        "time": "2021-09-01T05:57:43.144Z",
                        "user": "bltc359c2d884f0888e",
                        "version": 1
                    },
                    {
                        "environment": "blt3e578964e5ba0afe",
                        "locale": "en-us",
                        "time": "2021-09-01T05:57:43.144Z",
                        "user": "bltc359c2d884f0888e",
                        "version": 1
                    }
                ]
            },
            {
                "uid": "blt2f705cacdc5957db",
                "created_at": "2021-09-01T05:56:42.269Z",
                "updated_at": "2021-09-01T05:56:42.269Z",
                "content_type": "image/png",
                "file_size": "19786",
                "tags": [],
                "filename": "MVMT_Rallye_Green_Sandstone_3.png",
                "url": "https://images.contentstack.io/v3/assets/bltc91ab68f0b5e7b84/blt2f705cacdc5957db/612f161a932fbb12e7dc7519/MVMT_Rallye_Green_Sandstone_3.png",
                "ACL": [],
                "is_dir": false,
                "parent_uid": null,
                "_version": 1,
                "title": "MVMT_Rallye_Green_Sandstone_3.png",
                "publish_details": [
                    {
                        "environment": "blt0677a9c52fcd5de1",
                        "locale": "en-us",
                        "time": "2021-09-01T05:56:43.975Z",
                        "user": "bltc359c2d884f0888e",
                        "version": 1
                    },
                    {
                        "environment": "blt3e578964e5ba0afe",
                        "locale": "en-us",
                        "time": "2021-09-01T05:56:43.975Z",
                        "user": "bltc359c2d884f0888e",
                        "version": 1
                    },
                    {
                        "environment": "bltf9d34c6dfb34d221",
                        "locale": "en-us",
                        "time": "2021-09-01T05:56:43.975Z",
                        "user": "bltc359c2d884f0888e",
                        "version": 1
                    }
                ]
            },
            {
                "uid": "blteccabffada65846c",
                "created_at": "2021-09-01T05:56:38.878Z",
                "updated_at": "2021-09-01T05:56:38.878Z",
                "content_type": "image/png",
                "file_size": "22168",
                "tags": [],
                "filename": "MVMT_Rallye_Green_Sandstone_2.png",
                "url": "https://images.contentstack.io/v3/assets/bltc91ab68f0b5e7b84/blteccabffada65846c/612f1616981a381cf3358c3a/MVMT_Rallye_Green_Sandstone_2.png",
                "ACL": [],
                "is_dir": false,
                "_version": 1,
                "title": "MVMT_Rallye_Green_Sandstone_2.png",
                "publish_details": [
                    {
                        "environment": "bltf9d34c6dfb34d221",
                        "locale": "en-us",
                        "time": "2021-09-01T05:56:40.698Z",
                        "user": "bltc359c2d884f0888e",
                        "version": 1
                    },
                    {
                        "environment": "blt3e578964e5ba0afe",
                        "locale": "en-us",
                        "time": "2021-09-01T05:56:40.698Z",
                        "user": "bltc359c2d884f0888e",
                        "version": 1
                    },
                    {
                        "environment": "blt0677a9c52fcd5de1",
                        "locale": "en-us",
                        "time": "2021-09-01T05:56:40.698Z",
                        "user": "bltc359c2d884f0888e",
                        "version": 1
                    }
                ]
            }
        ],
        "categories": [
            {
                "uid": "blt5cb2771ed6bcf69c",
                "_content_type_uid": "category"
            }
        ],
        "related_products": [
            {
                "uid": "blt7ec0e389746cae2e",
                "_content_type_uid": "product"
            },
            {
                "uid": "blt2eec3bb34477df60",
                "_content_type_uid": "product"
            }
        ],
        "tweet_text": "",
        "seo": {
            "description": "",
            "keyword": "",
            "block_indexing": false
        },
        "tags": [],
        "locale": "en-us",
        "ACL": {},
        "_in_progress": false,
        "number": 200,
        "extension_product_link": [],
        "uid": "bltceccaa78087a130e",
        "_version": 6,
        "publish_details": [
            {
                "environment": "blt3e578964e5ba0afe",
                "locale": "en-us",
                "time": "2021-09-09T07:03:13.184Z",
                "user": "bltd5d70bb484fce3ae",
                "version": 6
            },
            {
                "environment": "blt0677a9c52fcd5de1",
                "locale": "en-us",
                "time": "2021-09-09T07:03:13.144Z",
                "user": "bltd5d70bb484fce3ae",
                "version": 6
            },
            {
                "environment": "bltf9d34c6dfb34d221",
                "locale": "en-us",
                "time": "2021-09-09T07:03:13.149Z",
                "user": "bltd5d70bb484fce3ae",
                "version": 6
            }
        ]
    },
    "blt2eec3bb34477df60": {
        "title": "MVMT Rallye Green Sandstone",
        "url": "/product/blt2b37a83fd40469fd",
        "description": "Hand-painted moon, Moon retrograde with precision of 122 years, Moon returns backwards to zero at the end of its cycle every 29 days 12 hours and 44 minutes, Scratch resistant anti-reflective domed sapphire crystal, Crown decorated with a sapphire stone Swiss manual wind high precision mechanical movement with Haute Horlogerie finishing, Calibre G1769, 21'600 A/h (3Hz), Incabloc shock absorber, 29 jewels, Power reserve of 96 hours. Water resistant to 3 ATM/30 meters/99 feet, Hand-sewn blue alligator leather strap , 18k white gold push button deployment buckle, Fits up to a 10 inch wrist",
        "featured_image": [
            {
                "uid": "blte6118b938cab2d2a",
                "created_at": "2021-09-01T05:58:38.279Z",
                "updated_at": "2021-09-01T05:58:38.279Z",
                "content_type": "image/png",
                "file_size": "40794",
                "tags": [],
                "filename": "MVMT_Rallye_Green_Sandstone_1_(1).png",
                "url": "https://images.contentstack.io/v3/assets/bltc91ab68f0b5e7b84/blte6118b938cab2d2a/612f168e7cc1f70d96f2061a/MVMT_Rallye_Green_Sandstone_1_(1).png",
                "ACL": [],
                "is_dir": false,
                "_version": 1,
                "title": "MVMT_Rallye_Green_Sandstone_1_(1).png",
                "publish_details": [
                    {
                        "environment": "blt3e578964e5ba0afe",
                        "locale": "en-us",
                        "time": "2021-09-01T05:58:40.063Z",
                        "user": "bltc359c2d884f0888e",
                        "version": 1
                    },
                    {
                        "environment": "bltf9d34c6dfb34d221",
                        "locale": "en-us",
                        "time": "2021-09-01T05:58:40.063Z",
                        "user": "bltc359c2d884f0888e",
                        "version": 1
                    },
                    {
                        "environment": "blt0677a9c52fcd5de1",
                        "locale": "en-us",
                        "time": "2021-09-01T05:58:40.063Z",
                        "user": "bltc359c2d884f0888e",
                        "version": 1
                    }
                ]
            },
            {
                "uid": "blt2f705cacdc5957db",
                "created_at": "2021-09-01T05:56:42.269Z",
                "updated_at": "2021-09-01T05:56:42.269Z",
                "content_type": "image/png",
                "file_size": "19786",
                "tags": [],
                "filename": "MVMT_Rallye_Green_Sandstone_3.png",
                "url": "https://images.contentstack.io/v3/assets/bltc91ab68f0b5e7b84/blt2f705cacdc5957db/612f161a932fbb12e7dc7519/MVMT_Rallye_Green_Sandstone_3.png",
                "ACL": [],
                "is_dir": false,
                "parent_uid": null,
                "_version": 1,
                "title": "MVMT_Rallye_Green_Sandstone_3.png",
                "publish_details": [
                    {
                        "environment": "blt0677a9c52fcd5de1",
                        "locale": "en-us",
                        "time": "2021-09-01T05:56:43.975Z",
                        "user": "bltc359c2d884f0888e",
                        "version": 1
                    },
                    {
                        "environment": "blt3e578964e5ba0afe",
                        "locale": "en-us",
                        "time": "2021-09-01T05:56:43.975Z",
                        "user": "bltc359c2d884f0888e",
                        "version": 1
                    },
                    {
                        "environment": "bltf9d34c6dfb34d221",
                        "locale": "en-us",
                        "time": "2021-09-01T05:56:43.975Z",
                        "user": "bltc359c2d884f0888e",
                        "version": 1
                    }
                ]
            },
            {
                "uid": "blteccabffada65846c",
                "created_at": "2021-09-01T05:56:38.878Z",
                "updated_at": "2021-09-01T05:56:38.878Z",
                "content_type": "image/png",
                "file_size": "22168",
                "tags": [],
                "filename": "MVMT_Rallye_Green_Sandstone_2.png",
                "url": "https://images.contentstack.io/v3/assets/bltc91ab68f0b5e7b84/blteccabffada65846c/612f1616981a381cf3358c3a/MVMT_Rallye_Green_Sandstone_2.png",
                "ACL": [],
                "is_dir": false,
                "_version": 1,
                "title": "MVMT_Rallye_Green_Sandstone_2.png",
                "publish_details": [
                    {
                        "environment": "bltf9d34c6dfb34d221",
                        "locale": "en-us",
                        "time": "2021-09-01T05:56:40.698Z",
                        "user": "bltc359c2d884f0888e",
                        "version": 1
                    },
                    {
                        "environment": "blt3e578964e5ba0afe",
                        "locale": "en-us",
                        "time": "2021-09-01T05:56:40.698Z",
                        "user": "bltc359c2d884f0888e",
                        "version": 1
                    },
                    {
                        "environment": "blt0677a9c52fcd5de1",
                        "locale": "en-us",
                        "time": "2021-09-01T05:56:40.698Z",
                        "user": "bltc359c2d884f0888e",
                        "version": 1
                    }
                ]
            }
        ],
        "categories": [
            {
                "uid": "blt5cb2771ed6bcf69c",
                "_content_type_uid": "category"
            }
        ],
        "related_products": [
            {
                "uid": "blt7ec0e389746cae2e",
                "_content_type_uid": "product"
            },
            {
                "uid": "bltceccaa78087a130e",
                "_content_type_uid": "product"
            }
        ],
        "tweet_text": "",
        "tags": [],
        "locale": "en-us",
        "ACL": {},
        "seo": {
            "description": "",
            "keyword": "",
            "block_indexing": false
        },
        "_in_progress": false,
        "number": 180,
        "extension_product_link": [],
        "uid": "blt2eec3bb34477df60",
        "_version": 7,
        "publish_details": [
            {
                "environment": "bltf9d34c6dfb34d221",
                "locale": "en-us",
                "time": "2021-09-09T07:03:13.085Z",
                "user": "bltd5d70bb484fce3ae",
                "version": 7
            },
            {
                "environment": "blt0677a9c52fcd5de1",
                "locale": "en-us",
                "time": "2021-09-09T07:03:13.038Z",
                "user": "bltd5d70bb484fce3ae",
                "version": 7
            },
            {
                "environment": "blt3e578964e5ba0afe",
                "locale": "en-us",
                "time": "2021-09-09T07:03:13.027Z",
                "user": "bltd5d70bb484fce3ae",
                "version": 7
            }
        ]
    },
    "blt46db151f0b8fb105": {
        "title": "Oppenheimer's Lux Jacket - Brown",
        "url": "/product/bltefc07b7111472484",
        "description": "Synonymous with youth and modernity, luxury fashion house Oppenhiemer's was originally founded in 1961. Today the label runs under the current creative direction who continues to champion the brands core values. This brown leather and cotton blend zipped biker jacket is a staple piece and features classic lapels, long sleeves, a front zip fastening, a side zip detail and micro stud details.",
        "featured_image": [
            {
                "uid": "bltd09eaf92b027361a",
                "created_at": "2021-09-01T05:58:48.529Z",
                "updated_at": "2021-09-01T05:58:48.529Z",
                "content_type": "image/png",
                "file_size": "61244",
                "tags": [],
                "filename": "Golden_Bear_Steerhide_Moto.png",
                "url": "https://images.contentstack.io/v3/assets/bltc91ab68f0b5e7b84/bltd09eaf92b027361a/612f169819e7e2227aa3e61d/Golden_Bear_Steerhide_Moto.png",
                "ACL": [],
                "is_dir": false,
                "_version": 1,
                "title": "Golden_Bear_Steerhide_Moto.png",
                "publish_details": [
                    {
                        "environment": "blt0677a9c52fcd5de1",
                        "locale": "en-us",
                        "time": "2021-09-01T05:58:50.351Z",
                        "user": "bltc359c2d884f0888e",
                        "version": 1
                    },
                    {
                        "environment": "blt3e578964e5ba0afe",
                        "locale": "en-us",
                        "time": "2021-09-01T05:58:50.351Z",
                        "user": "bltc359c2d884f0888e",
                        "version": 1
                    },
                    {
                        "environment": "bltf9d34c6dfb34d221",
                        "locale": "en-us",
                        "time": "2021-09-01T05:58:50.350Z",
                        "user": "bltc359c2d884f0888e",
                        "version": 1
                    }
                ]
            },
            {
                "uid": "blt8881e3fd7efa3889",
                "created_at": "2021-09-01T05:56:08.988Z",
                "updated_at": "2021-09-01T05:56:08.988Z",
                "content_type": "image/png",
                "file_size": "232940",
                "tags": [],
                "filename": "Golden_Bear_Steerhide_Moto_(2).png",
                "url": "https://images.contentstack.io/v3/assets/bltc91ab68f0b5e7b84/blt8881e3fd7efa3889/612f15f867a2530f06655d5f/Golden_Bear_Steerhide_Moto_(2).png",
                "ACL": [],
                "is_dir": false,
                "_version": 1,
                "title": "Golden_Bear_Steerhide_Moto_(2).png",
                "publish_details": [
                    {
                        "environment": "blt0677a9c52fcd5de1",
                        "locale": "en-us",
                        "time": "2021-09-01T05:56:10.786Z",
                        "user": "bltc359c2d884f0888e",
                        "version": 1
                    },
                    {
                        "environment": "bltf9d34c6dfb34d221",
                        "locale": "en-us",
                        "time": "2021-09-01T05:56:10.786Z",
                        "user": "bltc359c2d884f0888e",
                        "version": 1
                    },
                    {
                        "environment": "blt3e578964e5ba0afe",
                        "locale": "en-us",
                        "time": "2021-09-01T05:56:10.786Z",
                        "user": "bltc359c2d884f0888e",
                        "version": 1
                    }
                ]
            },
            {
                "uid": "blt33ca8f4afcc8b698",
                "created_at": "2021-09-01T05:55:45.028Z",
                "updated_at": "2021-09-01T05:55:45.028Z",
                "content_type": "image/png",
                "file_size": "61244",
                "tags": [],
                "filename": "Golden_Bear_Steerhide_Moto_(1).png",
                "url": "https://images.contentstack.io/v3/assets/bltc91ab68f0b5e7b84/blt33ca8f4afcc8b698/612f15e134696214560981ae/Golden_Bear_Steerhide_Moto_(1).png",
                "ACL": [],
                "is_dir": false,
                "_version": 1,
                "title": "Golden_Bear_Steerhide_Moto_(1).png",
                "publish_details": [
                    {
                        "environment": "blt0677a9c52fcd5de1",
                        "locale": "en-us",
                        "time": "2021-09-01T05:55:46.715Z",
                        "user": "bltc359c2d884f0888e",
                        "version": 1
                    },
                    {
                        "environment": "blt3e578964e5ba0afe",
                        "locale": "en-us",
                        "time": "2021-09-01T05:55:46.715Z",
                        "user": "bltc359c2d884f0888e",
                        "version": 1
                    },
                    {
                        "environment": "bltf9d34c6dfb34d221",
                        "locale": "en-us",
                        "time": "2021-09-01T05:55:46.715Z",
                        "user": "bltc359c2d884f0888e",
                        "version": 1
                    }
                ]
            }
        ],
        "categories": [
            {
                "uid": "blt073302c68bb3b3f7",
                "_content_type_uid": "category"
            }
        ],
        "related_products": [
            {
                "uid": "blt06593f89b4b0207d",
                "_content_type_uid": "product"
            }
        ],
        "tweet_text": "",
        "seo": {
            "description": "",
            "keyword": "",
            "block_indexing": false
        },
        "tags": [],
        "locale": "en-us",
        "ACL": {},
        "_in_progress": false,
        "number": 434,
        "extension_product_link": [],
        "uid": "blt46db151f0b8fb105",
        "_version": 6,
        "publish_details": [
            {
                "environment": "blt3e578964e5ba0afe",
                "locale": "en-us",
                "time": "2021-09-09T07:03:13.741Z",
                "user": "bltd5d70bb484fce3ae",
                "version": 6
            },
            {
                "environment": "blt0677a9c52fcd5de1",
                "locale": "en-us",
                "time": "2021-09-09T07:03:13.769Z",
                "user": "bltd5d70bb484fce3ae",
                "version": 6
            },
            {
                "environment": "bltf9d34c6dfb34d221",
                "locale": "en-us",
                "time": "2021-09-09T07:03:13.761Z",
                "user": "bltd5d70bb484fce3ae",
                "version": 6
            }
        ]
    },
    "blt7f6a22a1a5ba14e9": {
        "title": "Low-Cut Boot in Brown Stretch Fit",
        "url": "/product/blt5e0de3e155d05a60",
        "description": "Kumar paves the way to a professional look with these cap-toe oxfordspunctuated with distinctive detailing.Cap toe<p>Lace-up closure with blind eyelets Broguing details.The tan shoes come with matching and burgundy laces; the black shoes come with matching and blue laces Full length padded footbed Leather upper; man-made sole Imported.",
        "featured_image": [
            {
                "uid": "blt64d32022e98a50d3",
                "created_at": "2021-09-01T05:59:22.536Z",
                "updated_at": "2021-09-01T05:59:22.536Z",
                "content_type": "image/png",
                "file_size": "35670",
                "tags": [],
                "filename": "Danner_Mountain_Light.png",
                "url": "https://images.contentstack.io/v3/assets/bltc91ab68f0b5e7b84/blt64d32022e98a50d3/612f16ba70a3831078ba60f6/Danner_Mountain_Light.png",
                "ACL": [],
                "is_dir": false,
                "_version": 1,
                "title": "Danner_Mountain_Light.png",
                "publish_details": [
                    {
                        "environment": "blt3e578964e5ba0afe",
                        "locale": "en-us",
                        "time": "2021-09-01T05:59:24.351Z",
                        "user": "bltc359c2d884f0888e",
                        "version": 1
                    },
                    {
                        "environment": "blt0677a9c52fcd5de1",
                        "locale": "en-us",
                        "time": "2021-09-01T05:59:24.351Z",
                        "user": "bltc359c2d884f0888e",
                        "version": 1
                    },
                    {
                        "environment": "bltf9d34c6dfb34d221",
                        "locale": "en-us",
                        "time": "2021-09-01T05:59:24.351Z",
                        "user": "bltc359c2d884f0888e",
                        "version": 1
                    }
                ]
            },
            {
                "uid": "bltc6b0aa64c7755f3d",
                "created_at": "2021-09-01T05:57:02.844Z",
                "updated_at": "2021-09-01T05:57:02.844Z",
                "content_type": "image/jpeg",
                "file_size": "3317",
                "tags": [],
                "filename": "Low-Cut.jpg",
                "url": "https://images.contentstack.io/v3/assets/bltc91ab68f0b5e7b84/bltc6b0aa64c7755f3d/612f162e360ae3147c553401/Low-Cut.jpg",
                "ACL": [],
                "is_dir": false,
                "_version": 1,
                "title": "Low-Cut.jpg",
                "publish_details": [
                    {
                        "environment": "blt3e578964e5ba0afe",
                        "locale": "en-us",
                        "time": "2021-09-01T05:57:05.066Z",
                        "user": "bltc359c2d884f0888e",
                        "version": 1
                    },
                    {
                        "environment": "bltf9d34c6dfb34d221",
                        "locale": "en-us",
                        "time": "2021-09-01T05:57:05.066Z",
                        "user": "bltc359c2d884f0888e",
                        "version": 1
                    },
                    {
                        "environment": "blt0677a9c52fcd5de1",
                        "locale": "en-us",
                        "time": "2021-09-01T05:57:05.066Z",
                        "user": "bltc359c2d884f0888e",
                        "version": 1
                    }
                ]
            },
            {
                "uid": "blte52c254d156fb7a3",
                "created_at": "2021-09-01T05:56:53.213Z",
                "updated_at": "2021-09-01T05:56:53.213Z",
                "content_type": "image/jpeg",
                "file_size": "2938",
                "tags": [],
                "filename": "Low-Cut_(1).jpg",
                "url": "https://images.contentstack.io/v3/assets/bltc91ab68f0b5e7b84/blte52c254d156fb7a3/612f162575cb5a207a75862a/Low-Cut_(1).jpg",
                "ACL": [],
                "is_dir": false,
                "_version": 1,
                "title": "Low-Cut_(1).jpg",
                "publish_details": [
                    {
                        "environment": "bltf9d34c6dfb34d221",
                        "locale": "en-us",
                        "time": "2021-09-01T05:56:54.827Z",
                        "user": "bltc359c2d884f0888e",
                        "version": 1
                    },
                    {
                        "environment": "blt0677a9c52fcd5de1",
                        "locale": "en-us",
                        "time": "2021-09-01T05:56:54.827Z",
                        "user": "bltc359c2d884f0888e",
                        "version": 1
                    },
                    {
                        "environment": "blt3e578964e5ba0afe",
                        "locale": "en-us",
                        "time": "2021-09-01T05:56:54.827Z",
                        "user": "bltc359c2d884f0888e",
                        "version": 1
                    }
                ]
            }
        ],
        "categories": [
            {
                "uid": "blt073302c68bb3b3f7",
                "_content_type_uid": "category"
            }
        ],
        "related_products": [],
        "tweet_text": "",
        "seo": {
            "description": "",
            "keyword": "",
            "block_indexing": false
        },
        "tags": [],
        "locale": "en-us",
        "ACL": {},
        "_in_progress": false,
        "number": 550,
        "extension_product_link": [],
        "uid": "blt7f6a22a1a5ba14e9",
        "_version": 6,
        "publish_details": [
            {
                "environment": "blt3e578964e5ba0afe",
                "locale": "en-us",
                "time": "2021-09-09T07:03:13.770Z",
                "user": "bltd5d70bb484fce3ae",
                "version": 6
            },
            {
                "environment": "bltf9d34c6dfb34d221",
                "locale": "en-us",
                "time": "2021-09-09T07:03:13.839Z",
                "user": "bltd5d70bb484fce3ae",
                "version": 6
            },
            {
                "environment": "blt0677a9c52fcd5de1",
                "locale": "en-us",
                "time": "2021-09-09T07:03:13.838Z",
                "user": "bltd5d70bb484fce3ae",
                "version": 6
            }
        ]
    }
}